Metadata-Version: 2.1
Name: ugly-csv-generator
Version: 1.1.2
Summary: Python package to generate ugly real-looking csvs.
Home-page: https://github.com/LucaCappelletti94/ugly_csv_generator
Author: LucaCappelletti94
Author-email: cappelletti.luca94@gmail.com
License: MIT
Classifier: Development Status :: 5 - Production/Stable
Classifier: License :: OSI Approved :: MIT License
Classifier: Programming Language :: Python :: 3
Requires-Python: >=3.9
Provides-Extra: test
License-File: LICENSE
